refyne/__init__.py
refyne/cache.py
refyne/client.py
refyne/errors.py
refyne/interfaces.py
refyne/types.py
refyne/version.py
refyne-0.1.46.dist-info/METADATA
refyne-0.1.46.dist-info/WHEEL
refyne-0.1.46.dist-info/licenses/LICENSE
refyne-0.1.46.dist-info/RECORD
