Metadata-Version: 2.4
Name: refyne
Version: 0.1.46
Summary: Official Python SDK for the Refyne API - LLM-powered web extraction
Project-URL: Homepage, https://refyne.uk/docs/sdks/python
Project-URL: Documentation, https://refyne.uk/docs/sdks/python
Project-URL: Repository, https://github.com/jmylchreest/refyne-sdk-python
Project-URL: Issues, https://github.com/jmylchreest/refyne-sdk-python/issues
Author-email: Refyne <support@refyne.uk>
License: MIT
License-File: LICENSE
Keywords: api,extraction,llm,refyne,sdk,web-scraping
Classifier: Development Status :: 4 - Beta
Classifier: Intended Audience :: Developers
Classifier: License :: OSI Approved :: MIT License
Classifier: Operating System :: OS Independent
Classifier: Programming Language :: Python :: 3
Classifier: Programming Language :: Python :: 3.10
Classifier: Programming Language :: Python :: 3.11
Classifier: Programming Language :: Python :: 3.12
Classifier: Programming Language :: Python :: 3.13
Classifier: Topic :: Internet :: WWW/HTTP
Classifier: Topic :: Software Development :: Libraries :: Python Modules
Classifier: Typing :: Typed
Requires-Python: >=3.10
Requires-Dist: httpx>=0.25.0
Requires-Dist: pydantic>=2.0.0
Provides-Extra: dev
Requires-Dist: datamodel-code-generator[ruff]>=0.25.0; extra == 'dev'
Requires-Dist: mypy>=1.0.0; extra == 'dev'
Requires-Dist: pytest-asyncio>=0.21.0; extra == 'dev'
Requires-Dist: pytest-cov>=4.0.0; extra == 'dev'
Requires-Dist: pytest>=7.0.0; extra == 'dev'
Requires-Dist: respx>=0.20.0; extra == 'dev'
Requires-Dist: ruff>=0.1.0; extra == 'dev'
